HousePricePrediction_dakshinm/__init__.py
HousePricePrediction_dakshinm/ingest_data.py
HousePricePrediction_dakshinm/score.py
HousePricePrediction_dakshinm/train.py
HousePricePrediction_dakshinm-1.4.1.dist-info/METADATA
HousePricePrediction_dakshinm-1.4.1.dist-info/WHEEL
HousePricePrediction_dakshinm-1.4.1.dist-info/top_level.txt
HousePricePrediction_dakshinm-1.4.1.dist-info/RECORD
