Metadata-Version: 2.1
Name: HousePricePrediction_dakshinm
Version: 1.4.1
Summary: House Price Prediction package
Author-email: Dakshin Aravind M <dakshin.m@tigeranalytics.com>
Classifier: Programming Language :: Python :: 3
Classifier: License :: OSI Approved :: MIT License
Classifier: Operating System :: OS Independent
Requires-Python: >=3.8
